backtrader_plotting/__init__.py
backtrader_plotting/utils.py
backtrader_plotting/analyzer_tables/__init__.py
backtrader_plotting/analyzer_tables/annualreturn.py
backtrader_plotting/analyzer_tables/calmar.py
backtrader_plotting/analyzer_tables/drawdown.py
backtrader_plotting/analyzer_tables/leverage.py
backtrader_plotting/analyzer_tables/periodstats.py
backtrader_plotting/analyzer_tables/sharperatio.py
backtrader_plotting/analyzer_tables/sqn.py
backtrader_plotting/analyzer_tables/timereturn.py
backtrader_plotting/analyzer_tables/tradeanalyzers.py
backtrader_plotting/analyzer_tables/transactions.py
backtrader_plotting/analyzer_tables/vwr.py
backtrader_plotting/bokeh/__init__.py
backtrader_plotting/bokeh/bokeh.py
backtrader_plotting/bokeh/bokeh_webapp.py
backtrader_plotting/bokeh/datatable.py
backtrader_plotting/bokeh/figure.py
backtrader_plotting/bokeh/hover_container.py
backtrader_plotting/bokeh/labelizer.py
backtrader_plotting/bokeh/marker.py
backtrader_plotting/bokeh/optbrowser.py
backtrader_plotting/bokeh/utils.py
backtrader_plotting/bokeh/live/__init__.py
backtrader_plotting/bokeh/live/liveclient.py
backtrader_plotting/bokeh/live/plotlistener.py
backtrader_plotting/bokeh/templates/basic.css.j2
backtrader_plotting/bokeh/templates/basic.html.j2
backtrader_plotting/html/__init__.py
backtrader_plotting/html/metadata.py
backtrader_plotting/schemes/__init__.py
backtrader_plotting/schemes/blackly.py
backtrader_plotting/schemes/btscheme.py
backtrader_plotting/schemes/scheme.py
backtrader_plotting/schemes/tradimo.py
backtrader_plotting-2.0.0.dist-info/LICENSE
backtrader_plotting-2.0.0.dist-info/METADATA
backtrader_plotting-2.0.0.dist-info/WHEEL
backtrader_plotting-2.0.0.dist-info/top_level.txt
backtrader_plotting-2.0.0.dist-info/RECORD
