Metadata-Version: 2.1
Name: backtrader_plotting
Version: 2.0.0
Summary: Plotting package for Backtrader (Bokeh)
Home-page: https://github.com/verybadsoldier/backtrader_plotting
Author: verybadsolider
Author-email: vbs@springrts.de
License: GPLv3+
Project-URL: Bug Tracker, https://github.com/verybadsoldier/backtrader_plotting/issues
Project-URL: Documentation, https://github.com/verybadsoldier/backtrader_plotting/wiki
Project-URL: Source Code, https://github.com/verybadsoldier/backtrader_plotting
Project-URL: Demos, https://github.com/verybadsoldier/backtrader_plotting/tree/gh-pages
Keywords: trading,development,plotting,backtrader
Platform: UNKNOWN
Requires-Python: >=3.6
License-File: LICENSE
